guided_filter_pytorch/__init__.py
guided_filter_pytorch/box_filter.py
guided_filter_pytorch/guided_filter.py
guided_filter_pytorch-3.7.5.dist-info/METADATA
guided_filter_pytorch-3.7.5.dist-info/WHEEL
guided_filter_pytorch-3.7.5.dist-info/top_level.txt
guided_filter_pytorch-3.7.5.dist-info/zip-safe
guided_filter_pytorch-3.7.5.dist-info/RECORD
