Metadata-Version: 2.1
Name: guided-filter-pytorch
Version: 3.7.5
Summary: Deep Guided Filtering Layer for PyTorch
Home-page: https://github.com/wuhuikai/DeepGuidedFilter
Author: wuhuikai
Author-email: huikaiwu@icloud.com
License: UNKNOWN
Platform: UNKNOWN
